cognize/__init__.py
cognize/epistemic.py
cognize/meta_learning.py
cognize/network.py
cognize/perception.py
cognize/policies.py
cognize/py.typed
cognize-0.1.8.dist-info/licenses/LICENSE
cognize-0.1.8.dist-info/licenses/NOTICE.txt
cognize-0.1.8.dist-info/METADATA
cognize-0.1.8.dist-info/WHEEL
cognize-0.1.8.dist-info/top_level.txt
cognize-0.1.8.dist-info/RECORD
