Metadata-Version: 2.4
Name: cognize
Version: 0.1.8
Summary: Programmable cognition for Python systems.
Home-page: https://github.com/heraclitus0/cognize
Author: Pulikanti Sashi Bharadwaj
Author-email: Pulikanti Sashi Bharadwaj <bharadwajpulikanti11@gmail.com>
License: Apache-2.0
Project-URL: Homepage, https://github.com/heraclitus0/cognize
Project-URL: Source, https://github.com/heraclitus0/cognize
Project-URL: Issues, https://github.com/heraclitus0/cognize/issues
Project-URL: UserGuide, https://github.com/heraclitus0/cognize/blob/main/docs/USER_GUIDE.md
Keywords: cognition,epistemic,rupture,projection,AI,symbolic,drift
Classifier: Development Status :: 4 - Beta
Classifier: Programming Language :: Python :: 3 :: Only
Classifier: Programming Language :: Python :: 3.10
Classifier: Programming Language :: Python :: 3.11
Classifier: Programming Language :: Python :: 3.12
Classifier: License :: OSI Approved :: Apache Software License
Classifier: Operating System :: OS Independent
Classifier: Intended Audience :: Developers
Classifier: Topic :: Scientific/Engineering :: Artificial Intelligence
Requires-Python: >=3.10
License-File: LICENSE
License-File: NOTICE.txt
Requires-Dist: numpy>=1.26
Provides-Extra: viz
Requires-Dist: pandas>=2.2; extra == "viz"
Requires-Dist: matplotlib>=3.8; extra == "viz"
Requires-Dist: seaborn>=0.13; extra == "viz"
Provides-Extra: dev
Requires-Dist: pytest>=7; extra == "dev"
Requires-Dist: ruff>=0.4; extra == "dev"
Requires-Dist: mypy>=1.8; extra == "dev"
Requires-Dist: black>=23.12.1; extra == "dev"
Requires-Dist: build>=1.0.3; extra == "dev"
Requires-Dist: twine>=4.0.2; extra == "dev"
Provides-Extra: all
Requires-Dist: pandas>=2.2; extra == "all"
Requires-Dist: matplotlib>=3.8; extra == "all"
Requires-Dist: seaborn>=0.13; extra == "all"
Requires-Dist: pytest>=7; extra == "all"
Requires-Dist: ruff>=0.4; extra == "all"
Requires-Dist: mypy>=1.8; extra == "all"
Requires-Dist: black>=23.12.1; extra == "all"
Requires-Dist: build>=1.0.3; extra == "all"
Requires-Dist: twine>=4.0.2; extra == "all"
Dynamic: author
Dynamic: home-page
Dynamic: license-file
Dynamic: requires-python
